genlog/__init__.py
genlog/client.py
genlog/conf.py
genlog/exception.py
genlog/helper.py
genlog/main.py
genlog-1.0.2.1.dist-info/DESCRIPTION.rst
genlog-1.0.2.1.dist-info/METADATA
genlog-1.0.2.1.dist-info/RECORD
genlog-1.0.2.1.dist-info/WHEEL
genlog-1.0.2.1.dist-info/entry_points.txt
genlog-1.0.2.1.dist-info/metadata.json
genlog-1.0.2.1.dist-info/top_level.txt
