Metadata-Version: 2.0
Name: genlog
Version: 1.0.2.1
Summary: genlog: a tool that can randomly generate logs and send them to specified host:port
Home-page: http://github.com/ilpan/GenerateLog
Author: ilpan
Author-email: pna.dev@outlook.com
License: MIT
Keywords: genlog python3
Platform: UNKNOWN
Classifier: Development Status :: 4 - Beta
Classifier: Environment :: Console
Classifier: Intended Audience :: Developers
Classifier: License :: OSI Approved :: MIT License
Classifier: Programming Language :: Python :: 3.6
Classifier: Topic :: Internet :: Log Analysis
Classifier: Topic :: Utilities
Requires-Python: >=3.6
